__init__.py
atgen/__init__.py
atgen/labellers/__init__.py
atgen/labellers/base_labeller.py
atgen/labellers/custom_llm_labeller.py
atgen/labellers/get_labeller.py
atgen/labellers/golden_labeller.py
atgen/labellers/human_labeller.py
atgen/labellers/labelling_utils.py
atgen/labellers/api_labellers/__init__.py
atgen/labellers/api_labellers/anthropic_labeller.py
atgen/labellers/api_labellers/openai_labeller.py
atgen/metrics/__init__.py
atgen/metrics/bart_score.py
atgen/metrics/big_bench_hard_metric.py
atgen/metrics/compute_metrics.py
atgen/metrics/deepeval_supported_models_and_metrics.py
atgen/metrics/metrics.py
atgen/run_scripts/__init__.py
atgen/run_scripts/run_active_learning.py
atgen/strategies/__init__.py
atgen/strategies/base_strategy.py
atgen/strategies/bleuvar.py
atgen/strategies/dual.py
atgen/strategies/get_strategy.py
atgen/strategies/graph_cut.py
atgen/strategies/hadas.py
atgen/strategies/huds.py
atgen/strategies/idds.py
atgen/strategies/nsp.py
atgen/strategies/random_strategy.py
atgen/strategies/te_delfy.py
atgen/strategies/unieval/__init__.py
atgen/strategies/unieval/evaluator.py
atgen/strategies/unieval/scorer.py
atgen/strategies/unieval/utils.py
atgen/utils/__init__.py
atgen/utils/check_performance_metrics.py
atgen/utils/check_required_performance.py
atgen/utils/combine_results.py
atgen/utils/constants.py
atgen/utils/find_response_token_ids_in_text.py
atgen/utils/generate.py
atgen/utils/get_embeddings.py
atgen/utils/get_initial_labeled_data.py
atgen/utils/get_last_workdir.py
atgen/utils/installers.py
atgen/utils/load_model_tokenizer.py
atgen/utils/main_decorator.py
atgen/utils/post_process_generations.py
atgen/utils/prepare_model_for_training.py
atgen/utils/resolvers.py
atgen/utils/save_labeled_data.py
atgen/utils/save_log_iter_results.py
atgen/utils/training_utils.py
atgen/utils/validate_and_fill_config.py
atgen/utils/data/__init__.py
atgen/utils/data/get_output_column_name_for_phase.py
atgen/utils/data/get_preprocess_function.py
atgen-0.1.0.dist-info/licenses/LICENSE.md
atgen-0.1.0.dist-info/METADATA
atgen-0.1.0.dist-info/WHEEL
atgen-0.1.0.dist-info/entry_points.txt
atgen-0.1.0.dist-info/top_level.txt
atgen-0.1.0.dist-info/RECORD
