Metadata-Version: 2.4
Name: atgen
Version: 0.1.0
Summary: Toolkit for Active Learning in Generative Tasks
Author-email: "List of contributors: https://github.com/Aktsvigun/atgen/graphs/contributors" <artemshelmanov@gmail.com>
Project-URL: Homepage, https://github.com/Aktsvigun/al-nlg
Project-URL: Bug Tracker, https://github.com/Aktsvigun/al-nlg/issues
Project-URL: Repository, https://github.com/Aktsvigun/al-nlg
Keywords: NLP,deep learning,transformer,pytorch,peft,inference,active learning
Classifier: Development Status :: 3 - Alpha
Classifier: Operating System :: OS Independent
Classifier: Programming Language :: Python :: 3
Classifier: Programming Language :: Python :: 3.9
Classifier: Programming Language :: Python :: 3.10
Classifier: Programming Language :: Python :: 3.11
Classifier: Programming Language :: Python :: 3.12
Classifier: Topic :: Scientific/Engineering :: Artificial Intelligence
Requires-Python: >=3.10
License-File: LICENSE.md
Requires-Dist: alignscore-SpeedOfMagic
Requires-Dist: accelerate==1.5.2
Requires-Dist: anthropic==0.49.0
Requires-Dist: benepar==0.2.0
Requires-Dist: bert-score==0.3.13
Requires-Dist: bitsandbytes==0.45.3
Requires-Dist: ctc_score==0.1.3
Requires-Dist: datasets==3.4.0
Requires-Dist: deepeval==2.5.5
Requires-Dist: evaluate==0.4.3
Requires-Dist: hydra-core==1.3.2
Requires-Dist: nltk==3.9.1
Requires-Dist: kaleido==0.2.1
Requires-Dist: omegaconf==2.3.0
Requires-Dist: openai==1.66.3
Requires-Dist: openpyxl==3.1.5
Requires-Dist: peft==0.14.0
Requires-Dist: plotly==5.23.0
Requires-Dist: protobuf==3.20.3
Requires-Dist: pytest==8.3.2
Requires-Dist: pytorch_lightning==2.5.0.post0
Requires-Dist: rake_nltk==1.0.6
Requires-Dist: reportlab==4.3.1
Requires-Dist: rouge==1.0.1
Requires-Dist: rouge-score==0.1.2
Requires-Dist: sacrebleu==2.4.1
Requires-Dist: spacy==3.7.5
Requires-Dist: streamlit==1.37.0
Requires-Dist: streamlit-authenticator==0.4.2
Requires-Dist: tabulate==0.9.0
Requires-Dist: transformers==4.52.4
Requires-Dist: trl==0.15.2
Requires-Dist: torchmetrics==1.4.1
Requires-Dist: unsloth==2025.3.17
Requires-Dist: vllm==0.8.1
Requires-Dist: xlrd==1.2.0
Dynamic: license-file
